CHANGES.txt
README.md
setup.py
djinn_profiles/__init__.py
djinn_profiles/urls.py
djinn_profiles/utils.py
djinn_profiles.egg-info/PKG-INFO
djinn_profiles.egg-info/SOURCES.txt
djinn_profiles.egg-info/dependency_links.txt
djinn_profiles.egg-info/entry_points.txt
djinn_profiles.egg-info/not-zip-safe
djinn_profiles.egg-info/requires.txt
djinn_profiles.egg-info/top_level.txt
djinn_profiles/forms/__init__.py
djinn_profiles/forms/userprofile.py
djinn_profiles/models/__init__.py
djinn_profiles/models/groupprofile.py
djinn_profiles/models/userpreferences.py
djinn_profiles/models/userprofile.py