Metadata-Version: 1.1
Name: djinn-profiles
Version: 1.0.6
Summary: Djinn Intranet user and group profiles
Home-page: https://github.com/PythonUnited/djinn_profiles
Author: PythonUnited
Author-email: info@pythonunited.com
License: beer-ware
Keywords: Djinn user group profile
Platform: UNKNOWN
Classifier: Development Status :: 5 - Production/Stable
Classifier: Framework :: Django
Classifier: Intended Audience :: Developers
Classifier: License :: Freely Distributable
Classifier: Programming Language :: Python
Classifier: Topic :: Internet :: WWW/HTTP :: Site Management
Classifier: Topic :: Software Development :: Libraries :: Application Frameworks
